tests/__init__.py
tests/change_workdir_test.py
tests/code_submission_test.py
tests/dataset_metadata_test.py
tests/docker_integration_test.py
tests/export_submission_from_jupyter_notebook_test.py
tests/input_run_mount_test.py
tests/ir_datasets_test.py
tests/ir_lab_sose_2024_test.py
tests/irds_id_translation_test.py
tests/jupyter_notebook_pipeline_construction_test.py
tests/load_rerank_data_test.py
tests/load_resources_test.py
tests/local_execution_integration_test.py
tests/mount_hf_model_test.py
tests/parsing_of_profiling_test.py
tests/pd_load_data_test.py
tests/print_license_agreement_test.py
tests/pt_document_processing_loader_test.py
tests/pt_from_retriever_for_re_ranking_submission_loader_test.py
tests/pt_from_retriever_submission_loader_test.py
tests/pt_query_processing_loader_test.py
tests/reneuir_2024_test.py
tests/rest_api_test.py
tests/test_dataset_upload_dry_run.py
tests/test_export_from_zenodo.py
tests/test_export_submission_environment.py
tests/test_io_utils.py
tests/test_persisting_run_files.py
tests/test_task_submissions.py
tests/test_tira_dataset_redirects.py
tests/test_tira_io_utils.py
tests/test_tira_redicrects.py
tests/test_tira_redicrects_merging.py
tests/test_utils.py
tests/tira_run_integration_test.py
tests/tirex_tracker_test.py
tests/trectools_from_retriever_submission_loader_test.py
tests/cmd/__init__.py
tests/cmd/test_forward_of_openai_api_keys.py
tests/cmd/test_guess_dataset.py
tests/cmd/test_guess_details.py
tests/cmd/test_run_monitored_cmd.py
tests/format_check/__init__.py
tests/format_check/pan25_generated_content_analysis.py
tests/format_check/test_check_format_document.py
tests/format_check/test_check_format_for_gen_ir_simulation.py
tests/format_check/test_check_format_for_long_eval.py
tests/format_check/test_check_format_for_non_existing_formats.py
tests/format_check/test_check_format_for_run_file_format.py
tests/format_check/test_check_format_for_text_alignment_corpus.py
tira-0.0.194.dist-info/licenses/LICENSE
tira-0.0.194.dist-info/METADATA
tira-0.0.194.dist-info/WHEEL
tira-0.0.194.dist-info/entry_points.txt
tira-0.0.194.dist-info/top_level.txt
tira-0.0.194.dist-info/RECORD
