Metadata-Version: 2.4
Name: tira
Version: 0.0.194
Summary: Simple access to the TIRA API.
Home-page: https://github.com/tira-io/tira
Author: Maik Fröbe
Author-email: maik.froebe@uni-weimar.de
Maintainer: Maik Fröbe
Project-URL: Bug Tracker, https://github.com/tira-io/tira/issues
Classifier: Programming Language :: Python :: 3
Classifier: Programming Language :: Python :: 3 :: Only
Classifier: Programming Language :: Python :: 3.7
Classifier: Programming Language :: Python :: 3.8
Classifier: Programming Language :: Python :: 3.9
Classifier: License :: OSI Approved :: MIT License
Classifier: Operating System :: OS Independent
Classifier: Intended Audience :: Science/Research
Classifier: Topic :: Scientific/Engineering
Requires-Python: >=3.7
License-File: LICENSE
Requires-Dist: requests==2.*,>=2.26
Requires-Dist: pandas
Requires-Dist: packaging
Requires-Dist: tqdm
Requires-Dist: gitpython
Requires-Dist: pyyaml
Requires-Dist: docker==7.*,>=7.1.0
Provides-Extra: test
Requires-Dist: pytest==8.*,>=8.0; extra == "test"
Requires-Dist: pytest-cov==5.*,>=5.0; extra == "test"
Requires-Dist: approvaltests; extra == "test"
Requires-Dist: evaluate; extra == "test"
Requires-Dist: parameterized; extra == "test"
Provides-Extra: dev
Requires-Dist: numpy==1.*; extra == "dev"
Provides-Extra: ir
Requires-Dist: pyterrier-alpha; extra == "ir"
Requires-Dist: python-terrier>=1.0; extra == "ir"
Requires-Dist: ir-datasets>=0.5.9; extra == "ir"
Requires-Dist: trectools; extra == "ir"
Provides-Extra: all
Requires-Dist: docker==7.*,>=7.1.0; extra == "all"
Requires-Dist: numpy==1.*; extra == "all"
Requires-Dist: pyterrier-alpha; extra == "all"
Requires-Dist: python-terrier>=1.0; extra == "all"
Requires-Dist: ir-datasets>=0.5.9; extra == "all"
Requires-Dist: trectools; extra == "all"
Dynamic: license-file
